{
    "epiENGAGE-ensemble_mean": {
        "target_end_date": [
            "2026-01-10",
            "2026-01-17",
            "2026-01-24",
            "2026-01-31"
        ],
        "q0.025": [
            5.51096511846869,
            4.55416054261379,
            3.79331781175271,
            3.42172553440416
        ],
        "q0.25": [
            7.72162005231893,
            6.96915152885716,
            6.25990521078486,
            6.29635455917153
        ],
        "q0.5": [
            10.7316293041507,
            10.1771175541145,
            9.80754604702114,
            9.97948663470355
        ],
        "q0.75": [
            14.1876348583686,
            13.8141368109596,
            13.9407997948539,
            14.0970224831576
        ],
        "q0.975": [
            19.1786604047806,
            20.7127469999286,
            22.4685043720958,
            24.1793947191201
        ]
    },
    "VTSanghani-PRIME": {
        "target_end_date": [
            "2026-01-10",
            "2026-01-17",
            "2026-01-24",
            "2026-01-31"
        ],
        "q0.025": [
            0.0,
            0.0,
            0.0,
            0.0
        ],
        "q0.25": [
            0.09206347394788941,
            0.0,
            0.0,
            2.3403764446241717
        ],
        "q0.5": [
            9.995962253659934,
            9.12704539139817,
            9.679304804037814,
            12.389475134217951
        ],
        "q0.75": [
            19.899861033371977,
            18.566544035348947,
            20.13138451562263,
            22.43857382381173
        ],
        "q0.975": [
            24.81435071029062,
            23.250590154238346,
            25.31789126285817,
            27.425114263170016
        ]
    },
    "epiENGAGE-baseline": {
        "target_end_date": [
            "2026-01-10",
            "2026-01-17",
            "2026-01-24",
            "2026-01-31"
        ],
        "q0.025": [
            11.2453400900901,
            10.1033313313313,
            9.30209084084085,
            9.01106031031031
        ],
        "q0.25": [
            12.4085510510511,
            12.3175,
            12.1996696696697,
            12.0658333333333
        ],
        "q0.5": [
            12.46,
            12.46,
            12.46,
            12.46
        ],
        "q0.75": [
            12.511448948949,
            12.61,
            12.71,
            12.8204454454454
        ],
        "q0.975": [
            13.6746599099099,
            15.0035608108108,
            15.5786979479479,
            16.1317717717718
        ]
    },
    "epiENGAGE-lop_norm": {
        "target_end_date": [
            "2026-01-10",
            "2026-01-17",
            "2026-01-24",
            "2026-01-31"
        ],
        "q0.025": [
            0.0105077722803312,
            0.0,
            0.0,
            0.227982308955472
        ],
        "q0.25": [
            8.11903926344249,
            6.92257571468301,
            5.87340783352572,
            5.40964386716926
        ],
        "q0.5": [
            11.6111023916236,
            10.8872233430103,
            10.1764173375592,
            9.81825578856348
        ],
        "q0.75": [
            13.0228068899267,
            13.0483935731233,
            13.0630609433408,
            13.3436857794741
        ],
        "q0.975": [
            23.6302691752073,
            23.1639054826173,
            25.3923641137842,
            27.4802274941876
        ]
    },
    "epiforecasts-dyngam": {
        "target_end_date": [
            "2026-01-10",
            "2026-01-17",
            "2026-01-24",
            "2026-01-31"
        ],
        "q0.025": [
            7.3817155,
            5.62511225,
            4.5489465,
            3.75870825
        ],
        "q0.25": [
            10.789575,
            10.04975,
            9.2892075,
            8.440605
        ],
        "q0.5": [
            13.2302,
            13.68715,
            13.3639,
            13.0194
        ],
        "q0.75": [
            16.079,
            17.4608,
            18.9407,
            19.03735
        ],
        "q0.975": [
            22.92506,
            28.36539,
            32.520425,
            36.5209475
        ]
    },
    "UT-GBQR": {
        "target_end_date": [
            "2026-01-10",
            "2026-01-17",
            "2026-01-24",
            "2026-01-31"
        ],
        "q0.025": [
            6.59648418765267,
            5.20583472081258,
            4.17796037828713,
            3.6697134093693
        ],
        "q0.25": [
            7.71909297086345,
            6.52724801825705,
            5.61277657913705,
            5.21553456129187
        ],
        "q0.5": [
            9.36523636323375,
            8.29020468850495,
            7.56578297737865,
            7.00863478200281
        ],
        "q0.75": [
            10.996559750391,
            10.3155344171009,
            9.55801010203646,
            8.61237256607659
        ],
        "q0.975": [
            14.4586100970741,
            15.8816232876771,
            17.624414803263,
            19.2299652173007
        ]
    },
    "UMass-alloy": {
        "target_end_date": [
            "2026-01-10",
            "2026-01-17",
            "2026-01-24",
            "2026-01-31"
        ],
        "q0.025": [
            2.3312858146006805,
            1.836524410925095,
            0.937591339635567,
            0.6691457023412017
        ],
        "q0.25": [
            7.598817765732199,
            5.95125962602874,
            4.197872305117557,
            3.419423456608306
        ],
        "q0.5": [
            8.606747903859633,
            7.321187690669155,
            5.968742453689239,
            5.019923257297004
        ],
        "q0.75": [
            11.451304559131167,
            10.117805602348199,
            8.363904356610423,
            7.57637058045404
        ],
        "q0.975": [
            20.02062130662849,
            21.062570746916727,
            21.301092846410036,
            21.589174843358023
        ]
    }
}