{
    "epiENGAGE-baseline": {
        "target_end_date": [
            "2025-12-27",
            "2026-01-03",
            "2026-01-10",
            "2026-01-17"
        ],
        "q0.025": [
            4.67875,
            3.76296621621622,
            3.59582357357357,
            3.18199149149149
        ],
        "q0.25": [
            6.16,
            6.04301801801802,
            5.8176951951952,
            5.70542792792793
        ],
        "q0.5": [
            6.22,
            6.22,
            6.22,
            6.22
        ],
        "q0.75": [
            6.28,
            6.41946696696697,
            6.61217967967968,
            6.69966216216216
        ],
        "q0.975": [
            7.76125,
            8.29594519519519,
            8.78310385385385,
            9.37010735735735
        ]
    },
    "epiforecasts-dyngam": {
        "target_end_date": [
            "2025-12-27",
            "2026-01-03",
            "2026-01-10",
            "2026-01-17"
        ],
        "q0.025": [
            3.9162085,
            3.52788875,
            2.9507085,
            2.33957325
        ],
        "q0.25": [
            5.6722475,
            5.7238725,
            5.5900925,
            5.052375
        ],
        "q0.5": [
            6.846405,
            7.56768,
            7.61225,
            7.199305
        ],
        "q0.75": [
            8.2223025,
            9.6204425,
            10.233175,
            10.41635
        ],
        "q0.975": [
            11.4784725,
            14.5392375,
            16.9184725,
            18.986435
        ]
    },
    "epiENGAGE-GBQR": {
        "target_end_date": [
            "2025-12-27",
            "2026-01-03",
            "2026-01-10",
            "2026-01-17"
        ],
        "q0.025": [
            1.938003810327,
            1.85050648188133,
            1.40594229153138,
            1.16493212031632
        ],
        "q0.25": [
            5.45371851024674,
            5.09387167886107,
            3.68829260774627,
            2.84082452803873
        ],
        "q0.5": [
            6.58009575304026,
            5.51751331961939,
            4.33954168876343,
            3.73877165130489
        ],
        "q0.75": [
            7.47089834340203,
            5.52744759774157,
            4.39485926675068,
            4.06074881486352
        ],
        "q0.975": [
            10.5827057025566,
            10.4928343074032,
            9.89252033949378,
            9.83283651335193
        ]
    }
}