{
    "epiforecasts-dyngam": {
        "target_end_date": [
            "2025-12-06",
            "2025-12-13",
            "2025-12-20",
            "2025-12-27"
        ],
        "q0.025": [
            0.6641869,
            0.645121475,
            0.612022375,
            0.6721225
        ],
        "q0.25": [
            1.3374225,
            1.5207775,
            1.7316625,
            1.8814275
        ],
        "q0.5": [
            1.83779,
            2.26597,
            2.695485,
            3.066815
        ],
        "q0.75": [
            2.4757,
            3.261605,
            4.169415,
            4.8418
        ],
        "q0.975": [
            4.31113575,
            6.50147924999999,
            9.29647175,
            11.2915825
        ]
    }
}