{
    "epiforecasts-dyngam": {
        "target_end_date": [
            "2025-12-06",
            "2025-12-13",
            "2025-12-20",
            "2025-12-27"
        ],
        "q0.025": [
            0.70983515,
            0.742392025,
            0.803141225,
            0.812565525
        ],
        "q0.25": [
            1.11311,
            1.31148,
            1.529435,
            1.650935
        ],
        "q0.5": [
            1.396785,
            1.694845,
            2.06949,
            2.3668
        ],
        "q0.75": [
            1.7110625,
            2.22092,
            2.777275,
            3.308075
        ],
        "q0.975": [
            2.47430325,
            3.50800149999999,
            4.6634315,
            5.8738365
        ]
    }
}