{
    "epiENGAGE-ensemble_mean": {
        "target_end_date": [
            "2025-11-22",
            "2025-11-29",
            "2025-12-06",
            "2025-12-13"
        ],
        "q0.025": [
            0.415539135614051,
            0.437978229278285,
            0.441280350864629,
            0.44290300922977
        ],
        "q0.25": [
            1.43294620541484,
            1.49145038264954,
            1.49445927702226,
            1.56433482180793
        ],
        "q0.5": [
            1.60517827040655,
            2.06393110206022,
            2.22040316575418,
            2.40382126238439
        ],
        "q0.75": [
            2.14463025745216,
            2.6527875833404,
            3.10901663507539,
            3.33941369485312
        ],
        "q0.975": [
            3.79740876324435,
            4.38215675394527,
            5.02787338287953,
            5.96318626238181
        ]
    },
    "epiENGAGE-baseline": {
        "target_end_date": [
            "2025-11-22",
            "2025-11-29",
            "2025-12-06",
            "2025-12-13"
        ],
        "q0.025": [
            0.0,
            0.0,
            0.0,
            0.0
        ],
        "q0.25": [
            1.26,
            1.02648648648649,
            0.763778778778779,
            0.634532032032032
        ],
        "q0.5": [
            1.33,
            1.33,
            1.33,
            1.33
        ],
        "q0.75": [
            1.4,
            1.64092342342342,
            1.90053303303303,
            2.03412162162162
        ],
        "q0.975": [
            3.02495195195195,
            3.64660585585586,
            3.98143068068068,
            4.53655505505505
        ]
    },
    "epiENGAGE-lop_norm": {
        "target_end_date": [
            "2025-11-22",
            "2025-11-29",
            "2025-12-06",
            "2025-12-13"
        ],
        "q0.025": [
            0.114174759734831,
            0.0399479712874531,
            0.0,
            0.0
        ],
        "q0.25": [
            1.29773478458482,
            1.29187924927175,
            1.31448530368082,
            1.32784978331488
        ],
        "q0.5": [
            1.54962414508766,
            1.80434507698407,
            2.07142032895939,
            2.29194628303879
        ],
        "q0.75": [
            1.99547027951307,
            2.77643010861295,
            3.15260536726177,
            3.53087287510511
        ],
        "q0.975": [
            4.91182188416842,
            5.668504114866,
            6.20860453353307,
            6.37866182832531
        ]
    },
    "epiforecasts-dyngam": {
        "target_end_date": [
            "2025-11-22",
            "2025-11-29",
            "2025-12-06",
            "2025-12-13"
        ],
        "q0.025": [
            0.8515956,
            0.925272775,
            0.95899315,
            0.9831923
        ],
        "q0.25": [
            1.2677775,
            1.460395,
            1.64355,
            1.804085
        ],
        "q0.5": [
            1.53005,
            1.850845,
            2.169675,
            2.45866
        ],
        "q0.75": [
            1.857445,
            2.3438875,
            2.83285,
            3.32236
        ],
        "q0.975": [
            2.572999,
            3.59411225,
            4.6478375,
            5.60629324999999
        ]
    },
    "epiENGAGE-GBQR": {
        "target_end_date": [
            "2025-11-22",
            "2025-11-29",
            "2025-12-06",
            "2025-12-13"
        ],
        "q0.025": [
            0.395021806842153,
            0.388661912834855,
            0.364847902593886,
            0.34551672768931
        ],
        "q0.25": [
            1.77106111624451,
            1.98746966146213,
            2.07604905228799,
            2.25438743339177
        ],
        "q0.5": [
            1.95548481121964,
            3.01094830618066,
            3.16153449726255,
            3.42280378715318
        ],
        "q0.75": [
            3.17644577235649,
            3.97355182659778,
            4.59366687219315,
            4.66175946293774
        ],
        "q0.975": [
            5.79427533778111,
            5.90575215597994,
            6.4543519679579,
            7.74671048209039
        ]
    }
}