{
    "epiforecasts-dyngam": {
        "target_end_date": [
            "2025-11-22",
            "2025-11-29",
            "2025-12-06",
            "2025-12-13"
        ],
        "q0.025": [
            0.154414475,
            0.15861255,
            0.172225725,
            0.1636876
        ],
        "q0.25": [
            0.3110835,
            0.367019,
            0.42199925,
            0.4715815
        ],
        "q0.5": [
            0.4271035,
            0.5268335,
            0.628335,
            0.747914
        ],
        "q0.75": [
            0.567764,
            0.7433145,
            0.94259775,
            1.13661
        ],
        "q0.975": [
            0.969302624999999,
            1.316594,
            1.87464275,
            2.56720475
        ]
    }
}