{
    "VTSanghani-PRIME": {
        "target_end_date": [
            "2025-12-27",
            "2026-01-03",
            "2026-01-10",
            "2026-01-17"
        ],
        "q0.025": [
            0.0,
            0.0,
            0.0,
            0.0
        ],
        "q0.25": [
            0.5656006355397474,
            0.0,
            0.0,
            0.0
        ],
        "q0.5": [
            5.740833959424249,
            4.134043354803184,
            2.8781775903073337,
            3.090223369937321
        ],
        "q0.75": [
            10.916067283308749,
            9.214512698269115,
            7.939214136385851,
            8.038516671495247
        ],
        "q0.975": [
            13.48410955752666,
            11.735531409961855,
            10.450589950440163,
            10.493947294300858
        ]
    },
    "epiENGAGE-baseline": {
        "target_end_date": [
            "2025-12-27",
            "2026-01-03",
            "2026-01-10",
            "2026-01-17"
        ],
        "q0.025": [
            1.96,
            1.09851001001001,
            0.10827027027027,
            0.0
        ],
        "q0.25": [
            5.07,
            4.85883383383383,
            4.47068318318318,
            4.19541291291291
        ],
        "q0.5": [
            5.17,
            5.17,
            5.17,
            5.17
        ],
        "q0.75": [
            5.27,
            5.52071071071071,
            5.89446696696697,
            6.13466966966967
        ],
        "q0.975": [
            8.38,
            9.04009134134133,
            10.1765755755756,
            10.4399614614615
        ]
    },
    "epiforecasts-dyngam": {
        "target_end_date": [
            "2025-12-27",
            "2026-01-03",
            "2026-01-10",
            "2026-01-17"
        ],
        "q0.025": [
            2.60357875,
            2.1797175,
            1.9591115,
            1.60736925
        ],
        "q0.25": [
            4.25885,
            4.2233475,
            4.05726,
            3.70635
        ],
        "q0.5": [
            5.48342,
            5.86808,
            5.997305,
            5.82739
        ],
        "q0.75": [
            6.9849225,
            8.14896,
            8.8024125,
            9.0612825
        ],
        "q0.975": [
            10.7440875,
            14.9983625,
            18.16903,
            19.7933975
        ]
    },
    "UMass-alloy": {
        "target_end_date": [
            "2025-12-27",
            "2026-01-03",
            "2026-01-10",
            "2026-01-17"
        ],
        "q0.025": [
            1.1201179321022225,
            0.9326165293012098,
            0.7888346783324393,
            0.645646527777107
        ],
        "q0.25": [
            6.714566580059865,
            6.233817923700126,
            6.299785341716318,
            5.546058997240925
        ],
        "q0.5": [
            9.112086827494267,
            9.664146102646338,
            9.499548656310484,
            8.573321965952548
        ],
        "q0.75": [
            10.829098015312198,
            12.295453986166264,
            11.915968634236481,
            11.543539711954617
        ],
        "q0.975": [
            16.611161799304806,
            18.268926505608245,
            19.156761677721853,
            19.46171777160888
        ]
    },
    "epiENGAGE-GBQR": {
        "target_end_date": [
            "2025-12-27",
            "2026-01-03",
            "2026-01-10",
            "2026-01-17"
        ],
        "q0.025": [
            0.618273657453625,
            0.583498171901013,
            0.496899771076426,
            0.450389898788465
        ],
        "q0.25": [
            5.9278456820187,
            5.82447411875389,
            4.65581591384119,
            2.94705749695019
        ],
        "q0.5": [
            8.22809614504362,
            8.16777823384439,
            6.76973906582991,
            5.17736961950439
        ],
        "q0.75": [
            11.9959649812785,
            10.493009132975,
            7.63479016297698,
            6.80377429904491
        ],
        "q0.975": [
            15.2532329467076,
            15.2668624774522,
            15.122073208923,
            15.5081440991377
        ]
    }
}