{
    "epiENGAGE-ensemble_mean": {
        "target_end_date": [
            "2026-01-03",
            "2026-01-10",
            "2026-01-17",
            "2026-01-24"
        ],
        "q0.025": [
            8.77100986522404,
            7.92388520258767,
            6.83800596129752,
            5.8888074569109
        ],
        "q0.25": [
            12.231714526896,
            11.46918969377,
            10.4683941902935,
            9.65209374051212
        ],
        "q0.5": [
            15.4067258963116,
            15.1083160917851,
            14.3643648834173,
            13.6543344900265
        ],
        "q0.75": [
            19.3562403490228,
            19.7431222770301,
            19.249169378474,
            18.8126701497911
        ],
        "q0.975": [
            24.9250381890423,
            27.9010379717754,
            29.6633956653213,
            30.4453630638641
        ]
    },
    "VTSanghani-PRIME": {
        "target_end_date": [
            "2026-01-03",
            "2026-01-10",
            "2026-01-17",
            "2026-01-24"
        ],
        "q0.025": [
            0.0,
            0.0,
            0.0,
            0.0
        ],
        "q0.25": [
            1.7721188102856884,
            1.0006331972779923,
            0.43550688919005814,
            0.929624823255971
        ],
        "q0.5": [
            13.56380867559218,
            13.107987656602363,
            11.902846798507907,
            12.09805633853509
        ],
        "q0.75": [
            25.35549854089866,
            25.215342115926727,
            23.37018670782575,
            23.266487853814205
        ],
        "q0.975": [
            31.206743530920644,
            31.223225458498057,
            29.060483515129985,
            28.80846103125089
        ]
    },
    "epiENGAGE-baseline": {
        "target_end_date": [
            "2026-01-03",
            "2026-01-10",
            "2026-01-17",
            "2026-01-24"
        ],
        "q0.025": [
            12.86425,
            12.409954954955,
            12.0444874874875,
            11.6787462462462
        ],
        "q0.25": [
            14.11,
            14.0178428428428,
            13.91,
            13.7969994994995
        ],
        "q0.5": [
            14.15,
            14.15,
            14.15,
            14.15
        ],
        "q0.75": [
            14.19,
            14.27,
            14.36,
            14.4993218218218
        ],
        "q0.975": [
            15.43575,
            15.85079004004,
            16.1706754254254,
            16.4286456456456
        ]
    },
    "epiENGAGE-lop_norm": {
        "target_end_date": [
            "2026-01-03",
            "2026-01-10",
            "2026-01-17",
            "2026-01-24"
        ],
        "q0.025": [
            0.826894719561335,
            0.468656127451931,
            0.19219000387651,
            0.40655707896125
        ],
        "q0.25": [
            12.7211395180388,
            11.2747278568547,
            9.74019726994473,
            8.67302110065838
        ],
        "q0.5": [
            14.7128910830986,
            14.2279113465888,
            14.0878223789652,
            13.85509718704
        ],
        "q0.75": [
            19.9432509556371,
            21.0007052890892,
            20.796987030323,
            20.1520789816673
        ],
        "q0.975": [
            29.6070598285896,
            32.172157319665,
            35.4859102498927,
            36.3304799242328
        ]
    },
    "epiforecasts-dyngam": {
        "target_end_date": [
            "2026-01-03",
            "2026-01-10",
            "2026-01-17",
            "2026-01-24"
        ],
        "q0.025": [
            8.52875625,
            7.004135,
            5.94663075,
            4.9594585
        ],
        "q0.25": [
            12.8339,
            12.410575,
            11.79445,
            10.6605
        ],
        "q0.5": [
            15.70985,
            16.2125,
            16.06615,
            15.5198
        ],
        "q0.75": [
            18.767225,
            21.005775,
            21.827075,
            22.62955
        ],
        "q0.975": [
            26.4412225,
            31.5983075,
            37.2474775,
            39.49248
        ]
    },
    "NAU-Copycat": {
        "target_end_date": [
            "2026-01-03",
            "2026-01-10",
            "2026-01-17",
            "2026-01-24"
        ],
        "q0.025": [
            18.048226169158617,
            18.452290491620232,
            16.158555681743405,
            12.809676694155385
        ],
        "q0.25": [
            21.13301674500963,
            22.580730265190287,
            22.554495817082703,
            20.696865220742094
        ],
        "q0.5": [
            22.86737776900624,
            25.73802580755882,
            26.13337837263127,
            24.074654520395114
        ],
        "q0.75": [
            24.94987934695172,
            29.193932736669076,
            30.85608120286374,
            29.306878515254418
        ],
        "q0.975": [
            31.57247579779718,
            41.05788274763481,
            47.01166789923318,
            47.08272686958015
        ]
    },
    "UT-GBQR": {
        "target_end_date": [
            "2026-01-03",
            "2026-01-10",
            "2026-01-17",
            "2026-01-24"
        ],
        "q0.025": [
            9.6307898459161,
            8.3508803644306,
            6.75879459654355,
            5.99109638252145
        ],
        "q0.25": [
            13.2099930904941,
            11.5713957925515,
            9.80183251069115,
            8.57965078144054
        ],
        "q0.5": [
            14.4106097838564,
            12.6947452665682,
            11.3729136208727,
            10.5912087261259
        ],
        "q0.75": [
            16.3854030737782,
            14.5850707438411,
            13.1724544993021,
            12.5378260237428
        ],
        "q0.975": [
            19.7211357347975,
            20.5411780630513,
            20.7949024139763,
            21.1633714049207
        ]
    },
    "UMass-alloy": {
        "target_end_date": [
            "2026-01-03",
            "2026-01-10",
            "2026-01-17",
            "2026-01-24"
        ],
        "q0.025": [
            3.1581006959413696,
            2.640879624469515,
            1.7346502602303904,
            1.4282216368147276
        ],
        "q0.25": [
            9.429315068908762,
            7.722101243285805,
            5.474507416202749,
            4.430282945152007
        ],
        "q0.5": [
            11.328187391576611,
            9.784778033751362,
            8.160159781945573,
            7.060835490642058
        ],
        "q0.75": [
            16.7018518465372,
            15.618216964229974,
            13.92128318951412,
            12.146854514602767
        ],
        "q0.975": [
            22.88895227145398,
            24.954295295939144,
            26.570365748415337,
            26.49939353786464
        ]
    },
    "NAU-INFLAenza": {
        "target_end_date": [
            "2026-01-03",
            "2026-01-10",
            "2026-01-17",
            "2026-01-24"
        ],
        "q0.025": [
            9.16694609555218,
            6.60905598263835,
            5.222922953077767,
            4.3544527386385035
        ],
        "q0.25": [
            13.133657973573776,
            10.981049515241784,
            9.307966698887634,
            8.470732913494718
        ],
        "q0.5": [
            15.817247654149853,
            14.07017587801519,
            12.765105609963523,
            12.08578635448728
        ],
        "q0.75": [
            19.143824634993738,
            18.31351837854408,
            17.23710504981213,
            17.301772319301715
        ],
        "q0.975": [
            27.20898748832675,
            30.081586697264527,
            30.78819715506879,
            33.642462957786755
        ]
    }
}