{
    "epiENGAGE-ensemble_mean": {
        "target_end_date": [
            "2026-01-10",
            "2026-01-17",
            "2026-01-24",
            "2026-01-31"
        ],
        "q0.025": [
            4.01402085641446,
            3.33270363602804,
            2.76281042374771,
            2.48750347728289
        ],
        "q0.25": [
            6.27495475884664,
            5.44307252146652,
            5.05650504731222,
            4.9516723662579
        ],
        "q0.5": [
            8.43506121684266,
            7.86018396671766,
            7.77267666666827,
            7.6106503640769
        ],
        "q0.75": [
            10.9266263628447,
            10.6188831265236,
            10.7356811943818,
            10.5776850913439
        ],
        "q0.975": [
            15.1648058819169,
            16.6926312656974,
            18.0524435468813,
            18.890469536424
        ]
    },
    "VTSanghani-PRIME": {
        "target_end_date": [
            "2026-01-10",
            "2026-01-17",
            "2026-01-24",
            "2026-01-31"
        ],
        "q0.025": [
            0.0,
            0.0,
            0.0,
            0.0
        ],
        "q0.25": [
            1.8761510654044533,
            0.688406395399799,
            1.4253384561987996,
            2.9112949277359483
        ],
        "q0.5": [
            8.433632594301272,
            7.342732597971974,
            8.73007397584387,
            9.480061105202296
        ],
        "q0.75": [
            14.991114123198091,
            13.997058800544147,
            16.03480949548894,
            16.04882728266864
        ],
        "q0.975": [
            18.245052395100046,
            17.29905311175226,
            19.659548409163538,
            19.308365196705086
        ]
    },
    "epiENGAGE-baseline": {
        "target_end_date": [
            "2026-01-10",
            "2026-01-17",
            "2026-01-24",
            "2026-01-31"
        ],
        "q0.025": [
            8.33236336336336,
            7.74156181181181,
            7.21183858858859,
            7.00221696696697
        ],
        "q0.25": [
            9.43,
            9.34,
            9.23,
            9.12
        ],
        "q0.5": [
            9.48,
            9.48,
            9.48,
            9.48
        ],
        "q0.75": [
            9.53,
            9.61,
            9.73,
            9.87056306306306
        ],
        "q0.975": [
            10.6276366366366,
            11.1839331831832,
            11.5976989489489,
            11.9098375875876
        ]
    },
    "epiENGAGE-lop_norm": {
        "target_end_date": [
            "2026-01-10",
            "2026-01-17",
            "2026-01-24",
            "2026-01-31"
        ],
        "q0.025": [
            0.194267791524258,
            0.0960250162382437,
            0.213401240202731,
            0.447676482803407
        ],
        "q0.25": [
            6.46943369553758,
            5.43377151567698,
            4.71018312414262,
            4.26517295385588
        ],
        "q0.5": [
            8.82472388416858,
            8.18283595138866,
            7.61122006638306,
            7.26579060605171
        ],
        "q0.75": [
            9.98894477683142,
            9.91843668554718,
            10.0726086803505,
            10.2161729346932
        ],
        "q0.975": [
            17.822813126022,
            18.196287336099,
            19.9479831532405,
            20.8330343801648
        ]
    },
    "epiforecasts-dyngam": {
        "target_end_date": [
            "2026-01-10",
            "2026-01-17",
            "2026-01-24",
            "2026-01-31"
        ],
        "q0.025": [
            4.9680295,
            3.65478,
            2.7844065,
            2.2891045
        ],
        "q0.25": [
            7.8954275,
            7.1537125,
            6.5103525,
            5.7255675
        ],
        "q0.5": [
            10.154,
            10.12445,
            9.8205,
            9.47044
        ],
        "q0.75": [
            12.842275,
            13.9059,
            14.30335,
            14.64575
        ],
        "q0.975": [
            19.24034,
            25.2085575,
            28.18051,
            30.9038325
        ]
    },
    "UT-GBQR": {
        "target_end_date": [
            "2026-01-10",
            "2026-01-17",
            "2026-01-24",
            "2026-01-31"
        ],
        "q0.025": [
            5.10114528835664,
            4.0241254193175,
            3.16716431475988,
            2.6957521742386
        ],
        "q0.25": [
            6.13384846190341,
            5.21377084908747,
            4.6401753610961,
            4.14950906025449
        ],
        "q0.5": [
            7.20216515464667,
            6.365587303501,
            5.94703020209401,
            5.5453041270454
        ],
        "q0.75": [
            8.49221485910631,
            7.79607470940924,
            7.0171549908933,
            6.30525084780178
        ],
        "q0.975": [
            11.1928348308331,
            12.299811040793,
            13.3405463375505,
            14.5198747059342
        ]
    },
    "UMass-alloy": {
        "target_end_date": [
            "2026-01-10",
            "2026-01-17",
            "2026-01-24",
            "2026-01-31"
        ],
        "q0.025": [
            1.6685661303523105,
            1.2430509490108779,
            0.6506427153900632,
            0.45044374520890107
        ],
        "q0.25": [
            6.039346766925336,
            4.819472862845354,
            3.4766589192661987,
            2.8519903432990468
        ],
        "q0.5": [
            6.905508335265331,
            5.988149932115346,
            4.885779155403491,
            4.077446588136829
        ],
        "q0.75": [
            8.777527831919027,
            7.785382122664517,
            6.593091485526807,
            6.018034263186063
        ],
        "q0.975": [
            16.518165547014714,
            17.471801492758477,
            17.48391403874336,
            17.81043769189286
        ]
    }
}