{
    "VTSanghani-PRIME": {
        "target_end_date": [
            "2025-12-27",
            "2026-01-03",
            "2026-01-10",
            "2026-01-17"
        ],
        "q0.025": [
            0.0,
            0.0,
            0.0,
            0.0
        ],
        "q0.25": [
            1.8091673304563873,
            0.7594769324702196,
            0.0,
            0.0
        ],
        "q0.5": [
            6.671028927259928,
            5.8467650440285155,
            4.558395215145564,
            4.196788036489149
        ],
        "q0.75": [
            11.532890524063468,
            10.934053155586808,
            9.503865990218545,
            8.9125679243633
        ],
        "q0.975": [
            13.945432206844366,
            13.458455460563828,
            11.957896025479632,
            11.252621280426768
        ]
    },
    "epiENGAGE-baseline": {
        "target_end_date": [
            "2025-12-27",
            "2026-01-03",
            "2026-01-10",
            "2026-01-17"
        ],
        "q0.025": [
            2.6825,
            1.21871696696697,
            0.959642392392393,
            0.537201451451452
        ],
        "q0.25": [
            5.89,
            5.65879129129129,
            5.32541041041041,
            5.0890015015015
        ],
        "q0.5": [
            6.07,
            6.07,
            6.07,
            6.07
        ],
        "q0.75": [
            6.25,
            6.46644894894895,
            6.84837587587588,
            7.11931181181181
        ],
        "q0.975": [
            9.4575,
            10.7678085585586,
            11.1731701701702,
            11.6325963463463
        ]
    },
    "epiforecasts-dyngam": {
        "target_end_date": [
            "2025-12-27",
            "2026-01-03",
            "2026-01-10",
            "2026-01-17"
        ],
        "q0.025": [
            2.67170975,
            2.2280665,
            1.84284025,
            1.49173875
        ],
        "q0.25": [
            4.8727475,
            4.7263425,
            4.41951,
            3.93553
        ],
        "q0.5": [
            6.31913,
            6.659615,
            6.63536,
            6.29396
        ],
        "q0.75": [
            8.3147275,
            9.3884475,
            9.8377075,
            9.613005
        ],
        "q0.975": [
            13.13675,
            17.59846,
            20.6322725,
            22.49367
        ]
    },
    "UMass-alloy": {
        "target_end_date": [
            "2025-12-27",
            "2026-01-03",
            "2026-01-10",
            "2026-01-17"
        ],
        "q0.025": [
            1.8044642190109272,
            1.6230255413804096,
            1.425240375308533,
            1.200662023884093
        ],
        "q0.25": [
            7.608075053800276,
            7.887484209486868,
            8.35432995339472,
            7.762576608972163
        ],
        "q0.5": [
            10.126826633755002,
            11.42303274745866,
            11.536802348854412,
            11.038742693202435
        ],
        "q0.75": [
            12.67073627040083,
            14.403263540471936,
            14.84522600976316,
            14.715324704265454
        ],
        "q0.975": [
            18.914638188370265,
            20.55174339256587,
            21.6090471275456,
            22.784219157355007
        ]
    },
    "epiENGAGE-GBQR": {
        "target_end_date": [
            "2025-12-27",
            "2026-01-03",
            "2026-01-10",
            "2026-01-17"
        ],
        "q0.025": [
            1.0469114785585,
            1.0280744591,
            0.880999797207373,
            0.844828869725489
        ],
        "q0.25": [
            5.5261809477119,
            5.69044600066467,
            4.12271108297494,
            3.07156893194879
        ],
        "q0.5": [
            8.64587079477642,
            8.01451340221009,
            6.92077481365781,
            5.8278697931085
        ],
        "q0.75": [
            10.5895935328331,
            8.67540674779032,
            7.14133666984676,
            7.43347911356692
        ],
        "q0.975": [
            17.2874895761602,
            17.3019451142948,
            17.3210610153613,
            17.2324690990243
        ]
    }
}