{
    "epiENGAGE-baseline": {
        "target_end_date": [
            "2025-03-29",
            "2025-04-05",
            "2025-04-12",
            "2025-04-19",
            "2025-04-26"
        ],
        "q0.025": [
            1634.4292042042,
            1265.63746246246,
            651.364614614615,
            359.086061061061,
            194.397922922923
        ],
        "q0.25": [
            2668.36786786787,
            2552.19594594595,
            2456.77727727728,
            2371.12537537537,
            2306.10635635636
        ],
        "q0.5": [
            2773.0,
            2773.0,
            2773.0,
            2773.0,
            2773.0
        ],
        "q0.75": [
            2877.63213213213,
            3007.16366366366,
            3114.2042042042,
            3218.77452452452,
            3332.10885885886
        ],
        "q0.975": [
            3911.5707957958,
            4273.90890890891,
            5033.17362362362,
            5258.37334834834,
            5492.77332332332
        ]
    },
    "epiENGAGE-Copycat": {
        "target_end_date": [
            "2025-03-29",
            "2025-04-05",
            "2025-04-12",
            "2025-04-19",
            "2025-04-26"
        ],
        "q0.025": [
            2210,
            1916,
            1734,
            1587,
            1443
        ],
        "q0.25": [
            2514,
            2364,
            2225,
            2076,
            1934
        ],
        "q0.5": [
            2654,
            2560,
            2459,
            2318,
            2182
        ],
        "q0.75": [
            2793,
            2770,
            2696,
            2594,
            2466
        ],
        "q0.975": [
            3092,
            3168,
            3239,
            3162,
            3053
        ]
    },
    "epiforecasts-dyngam": {
        "target_end_date": [
            "2025-03-29",
            "2025-04-05",
            "2025-04-12",
            "2025-04-19",
            "2025-04-26"
        ],
        "q0.025": [
            2302.975,
            2117.95,
            2002.875,
            1853.0,
            1724.95
        ],
        "q0.25": [
            2552.75,
            2431.0,
            2352.0,
            2239.75,
            2127.0
        ],
        "q0.5": [
            2687.0,
            2610.0,
            2544.5,
            2475.0,
            2367.5
        ],
        "q0.75": [
            2821.25,
            2798.5,
            2772.0,
            2733.25,
            2641.5
        ],
        "q0.975": [
            3095.075,
            3228.05,
            3282.05,
            3295.025,
            3269.525
        ]
    }
}